COPYING
ChangeLog
INSTALL.txt
MANIFEST.in
README.txt
command_line_interface.html
command_line_interface.rst
eggtool.py
pkg-info.rst
pyrun.html
pyrun.py
pyrun.rst
pyrun.wpr
pyrunscripts.py
setup.py
./pyrun.py
examples/_testutils.py
examples/discover_and_run.html
examples/discover_and_run.rst
examples/examples-as-tests.txt
pyrun.egg-info/PKG-INFO
pyrun.egg-info/SOURCES.txt
pyrun.egg-info/dependency_links.txt
pyrun.egg-info/entry_points.txt
pyrun.egg-info/not-zip-safe
pyrun.egg-info/top_level.txt
sandbox/optionstester.py
sandbox/pyrequire.py
sandbox/test_pyrequire.py