Metadata-Version: 1.0
Name: pyrun
Version: 0.2.1a.dev
Summary: A convenient way to run python modules, packages and scripts with a dynamically discovered sys.path. Particularly useful when you want to make use of packages without installing them first, or to circumvent bootstrapping issues with complicated collections of python software.
Home-page: http://trac.wiretooth.com/public/wiki/pyrun
Author: Robin Bryce
Author-email: ['robinbryce@gmail.com']
License: MIT
Download-URL: http://svn.wiretooth.com/svn/open/pyrun/trunk/pyrun.py
Platform: UNKNOWN
Classifier: License :: OSI Approved :: MIT License
Classifier: Development Status :: 3 - Alpha
Classifier: Programming Language :: Python
Classifier: Intended Audience :: Developers
Classifier: Topic :: Software Development :: Libraries :: Python Modules
Classifier: Natural Language :: English
